v8cpu/__init__.py
v8cpu/cpu.py
v8cpu-1.0.2.dist-info/LICENSE
v8cpu-1.0.2.dist-info/METADATA
v8cpu-1.0.2.dist-info/WHEEL
v8cpu-1.0.2.dist-info/top_level.txt
v8cpu-1.0.2.dist-info/RECORD
