Metadata-Version: 2.1
Name: v8cpu
Version: 1.0.2
Summary: V8-CPU simulator of J. Glenn Brookshear’s book - 'Computer Science An Overview', Appendix C.
Home-page: https://github.com/747929791/v8cpu
Author: Yue Qin
Author-email: 747929791@qq.com
License: UNKNOWN
Platform: UNKNOWN
Classifier: Programming Language :: Python :: 3
Classifier: License :: OSI Approved :: MIT License
Classifier: Operating System :: OS Independent
Requires-Python: >=3.6
